jentic/apitools/openapi/traverse/datamodels/low/__init__.py
jentic/apitools/openapi/traverse/datamodels/low/introspection.py
jentic/apitools/openapi/traverse/datamodels/low/merge.py
jentic/apitools/openapi/traverse/datamodels/low/path.py
jentic/apitools/openapi/traverse/datamodels/low/py.typed
jentic/apitools/openapi/traverse/datamodels/low/traversal.py
jentic/apitools/openapi/traverse/json/__init__.py
jentic/apitools/openapi/traverse/json/py.typed
jentic/apitools/openapi/traverse/json/traversal.py
jentic_openapi_traverse-1.0.0a34.dist-info/licenses/LICENSE
jentic_openapi_traverse-1.0.0a34.dist-info/licenses/NOTICE
jentic_openapi_traverse-1.0.0a34.dist-info/WHEEL
jentic_openapi_traverse-1.0.0a34.dist-info/METADATA
jentic_openapi_traverse-1.0.0a34.dist-info/RECORD
