Metadata-Version: 2.4
Name: jentic-openapi-traverse
Version: 1.0.0a34
Summary: Jentic OpenAPI Traversal Utilities
Author: Jentic
Author-email: Jentic <hello@jentic.com>
License-Expression: Apache-2.0
License-File: LICENSE
License-File: NOTICE
Requires-Dist: jentic-openapi-datamodels~=1.0.0a34
Requires-Dist: jsonpointer~=3.0.0
Requires-Python: >=3.11
Project-URL: Homepage, https://github.com/jentic/jentic-openapi-tools
